eventhandler/baseclass.py
eventhandler/bash/runner.py
eventhandler/default/decider.py
eventhandler/json/__init__.py
eventhandler/json/logger.py
eventhandler/nsc_web/runner.py
eventhandler/omd_site_self_heal/decider.py
eventhandler/ssh/runner.py
eventhandler/text/__init__.py
eventhandler/text/logger.py
eventhandler/bin_folder/eventhandler
omdeventhandler-2.0.dist-info/METADATA
omdeventhandler-2.0.dist-info/WHEEL
omdeventhandler-2.0.dist-info/RECORD
