Metadata-Version: 2.4
Name: omdeventhandler
Version: 2.0
Summary: A framework for event handlers for OMD
Project-URL: Homepage, https://github.com/lausser/noteventificationforhandlerwarder
Project-URL: Bug Tracker, https://github.com/lausser/noteventificationforhandlerwarder/issues
Author-email: Gerhard Lausser <lausser@yahoo.com>
Classifier: License :: OSI Approved :: MIT License
Classifier: Operating System :: OS Independent
Classifier: Programming Language :: Python :: 3
Requires-Python: >=3.6
Requires-Dist: coshsh
Requires-Dist: jinja2
Provides-Extra: test
Requires-Dist: flake8; extra == 'test'
Requires-Dist: pytest; extra == 'test'
Requires-Dist: pytest-cov; extra == 'test'
Requires-Dist: requests; extra == 'test'
